prompt_blender/__init__.py
prompt_blender/__main__.py
prompt_blender/blend.py
prompt_blender/cache.py
prompt_blender/info.py
prompt_blender/model.py
prompt_blender/preferences.py
prompt_blender/result_file.py
prompt_blender/analysis/__init__.py
prompt_blender/analysis/analyse_results.py
prompt_blender/analysis/gpt_cost.py
prompt_blender/analysis/gpt_json.py
prompt_blender/gui/MainMenu.py
prompt_blender/gui/PromptNotebookPanel.py
prompt_blender/gui/__init__.py
prompt_blender/gui/config_model.py
prompt_blender/gui/main_wx.py
prompt_blender/gui/dialogs/ExecuteDialog.py
prompt_blender/gui/dialogs/InputListDialog.py
prompt_blender/gui/dialogs/PreferencesDialog.py
prompt_blender/gui/dialogs/ProgressDialog.py
prompt_blender/gui/dialogs/RunConfigurationsDialog.py
prompt_blender/gui/dialogs/__init__.py
prompt_blender/gui/examples/celsius_to_fahrenheit_simple.pbp
prompt_blender/gui/examples/english_translation.pbp
prompt_blender/gui/examples/lookup_weather_GPT.pbp
prompt_blender/gui/examples/temperature_conversion_bidirectional.pbp
prompt_blender/llms/browser_use.py
prompt_blender/llms/chatgpt.py
prompt_blender/llms/chatgpt_manual.py
prompt_blender/llms/dummy.py
prompt_blender/llms/execute_llm.py
prompt_blender/llms/groq.py
prompt_blender-0.2.3.dist-info/METADATA
prompt_blender-0.2.3.dist-info/WHEEL
prompt_blender-0.2.3.dist-info/entry_points.txt
prompt_blender-0.2.3.dist-info/licenses/LICENSE
prompt_blender-0.2.3.dist-info/RECORD
