Metadata-Version: 2.4
Name: prompt-blender
Version: 0.2.3
Summary: Tool designed to automate the generation, execution, and analysis of prompts for use in language learning models (LLMs). It simplifies the task of creating multiple prompts by automatically filling variables within a template, generating a Cartesian product of prompts, and analyzing the results returned by the model's API.
Project-URL: Repository, https://github.com/edanssandes/prompt-blender
Author: Edans Sandes
License: MIT License
License-File: LICENSE
Keywords: automation,cross product,gpt,llm,no code,prompt
Classifier: Development Status :: 4 - Beta
Classifier: Programming Language :: Python
Requires-Python: >=3.11
Requires-Dist: dirtyjson>=1.0.8
Requires-Dist: docx2txt>=0.8
Requires-Dist: dotenv>=0.9.9
Requires-Dist: groq>=0.11.0
Requires-Dist: mem0ai>=0.1.94
Requires-Dist: openai>=1.29.0
Requires-Dist: openpyxl>=3.1.2
Requires-Dist: pandas>=2.0.3
Requires-Dist: psutil>=7.0.0
Requires-Dist: pydantic>=2.11.3
Requires-Dist: pypdf>=6.1.3
Requires-Dist: pyperclip>=1.9.0
Requires-Dist: screeninfo>=0.8.1
Requires-Dist: uuid7==0.1.0
Requires-Dist: wxpython>=4.2.1
Requires-Dist: xlsxwriter>=3.2.3
Provides-Extra: browseruse
Requires-Dist: browser-use==0.1.48; extra == 'browseruse'
Requires-Dist: langchain-openai>=0.3.14; extra == 'browseruse'
Requires-Dist: playwright>=1.51.0; extra == 'browseruse'
